eve_utils/__init__.py
eve_utils/addins/__init__.py
eve_utils/addins/auth.py
eve_utils/addins/docker.py
eve_utils/addins/git.py
eve_utils/addins/serverless.py
eve_utils/addins/validation.py
eve_utils/addins/web_socket.py
eve_utils/code_gen/__init__.py
eve_utils/code_gen/authorization_inserter.py
eve_utils/code_gen/child_links_inserter.py
eve_utils/code_gen/domain_children_definition_inserter.py
eve_utils/code_gen/domain_definition_inserter.py
eve_utils/code_gen/domain_relations_inserter.py
eve_utils/code_gen/hooks_inserter.py
eve_utils/code_gen/parent_links_inserter.py
eve_utils/code_gen/validation_inserter.py
eve_utils/commands/__init__.py
eve_utils/commands/affordance.py
eve_utils/commands/api.py
eve_utils/commands/endpoint.py
eve_utils/commands/integration.py
eve_utils/commands/link.py
eve_utils/commands/optional_flags.py
eve_utils/commands/resource.py
eve_utils/commands/run.py
eve_utils/commands/setting.py
eve_utils/commands/singplu.py
eve_utils/skel/api/README.md
eve_utils/skel/api/_env.conf
eve_utils/skel/api/eve_service.py
eve_utils/skel/api/requirements.txt
eve_utils/skel/api/run.py
eve_utils/skel/api/settings.py
eve_utils/skel/api/.idea/icon.png
eve_utils/skel/api/.idea/icon_dark.png
eve_utils/skel/api/configuration/__init__.py
eve_utils/skel/api/configuration/settings.py
eve_utils/skel/api/domain/__init__.py
eve_utils/skel/api/domain/_common.py
eve_utils/skel/api/domain/_settings.py
eve_utils/skel/api/hooks/__init__.py
eve_utils/skel/api/hooks/_error_handlers.py
eve_utils/skel/api/hooks/_logs.py
eve_utils/skel/api/hooks/_settings.py
eve_utils/skel/api/log_trace/__init__.py
eve_utils/skel/api/log_trace/decorators.py
eve_utils/skel/api/log_trace/trace_level.py
eve_utils/skel/api/utils/__init__.py
eve_utils/skel/api/utils/gateway.py
eve_utils/skel/api/utils/log_setup.py
eve_utils/skel/api/utils/render.py
eve_utils/skel/auth/README.md
eve_utils/skel/auth/__init__.py
eve_utils/skel/auth/auth0.py
eve_utils/skel/auth/auth_handlers.py
eve_utils-0.9.43.dist-info/METADATA
eve_utils-0.9.43.dist-info/WHEEL
eve_utils-0.9.43.dist-info/entry_points.txt
eve_utils-0.9.43.dist-info/top_level.txt
eve_utils-0.9.43.dist-info/RECORD
