Metadata-Version: 2.1
Name: eve-utils
Version: 0.9.43
Summary: Templates and scripts to rapidly spin up a production-ready Eve-based API.
Home-page: https://github.com/pointw-dev/eve-utils
Author: Michael Ottoson
Author-email: michael@pointw.com
License: MIT
Classifier: Development Status :: 4 - Beta
Classifier: License :: OSI Approved :: MIT License
Classifier: Programming Language :: Python :: 3
Classifier: Operating System :: OS Independent
Classifier: Framework :: Flask
Classifier: Intended Audience :: Developers
Classifier: Topic :: Internet :: WWW/HTTP :: HTTP Servers
Classifier: Topic :: Software Development :: Code Generators
Classifier: Topic :: Utilities
Requires-Dist: libcst
Requires-Dist: inflect
Requires-Dist: click
